range_max_query/__init__.py
range_max_query/core.py
range_max_query-1.0.3.dist-info/LICENSE.txt
range_max_query-1.0.3.dist-info/METADATA
range_max_query-1.0.3.dist-info/WHEEL
range_max_query-1.0.3.dist-info/entry_points.txt
range_max_query-1.0.3.dist-info/top_level.txt
range_max_query-1.0.3.dist-info/RECORD
