Metadata-Version: 2.1
Name: range-max-query
Version: 1.0.3
Summary: Python implementation of range maximum query in O(logn).
Home-page: https://github.com/cassieHuanghahaha/rangeMaxQuery
Author: CassiezhHuang
Author-email: cassiehuang1111@gmail.com
License: MIT
Platform: UNKNOWN
Classifier: License :: OSI Approved :: MIT License
Classifier: Programming Language :: Python
Classifier: Programming Language :: Python :: 3
Classifier: Programming Language :: Python :: 3.6
Classifier: Programming Language :: Python :: Implementation :: CPython
Classifier: Programming Language :: Python :: Implementation :: PyPy
Requires-Python: >=3.6.0
